{ "CryptographicFailures": { "System": { "Provider": { "Name": "Microsoft-Windows-TLS", "Guid": "{C0FFEE00-ABCD-4321-9876-ABCDEF123456}" }, "EventID": "36880", "Version": "1", "Level": "0", "Task": "32", "Opcode": "0", "Keywords": "0x4000000000000000", "TimeCreated": { "SystemTime": "2023-11-20T11:00:00.654321Z" }, "EventRecordID": "1002", "Channel": "System", "Computer": "secure-client.local" }, "EventData": { "Protocol": "TLS 1.3", "CipherSuite": "TLS_AES_256_GCM_SHA384", "Result": "Successful", "User": "System" } } }